lastfmtools/bubble.py
lastfmtools/gif_creator.py
lastfmtools-0.1.0.dist-info/METADATA
lastfmtools-0.1.0.dist-info/WHEEL
lastfmtools-0.1.0.dist-info/RECORD
