Metadata-Version: 2.1
Name: lastfmtools
Version: 0.1.0
Summary: 
Author: Łukasz Błoch
Author-email: lkbloch7@gmail.com
Requires-Python: >=3.8,<4.0
Classifier: Programming Language :: Python :: 3
Classifier: Programming Language :: Python :: 3.8
Classifier: Programming Language :: Python :: 3.9
Classifier: Programming Language :: Python :: 3.10
Classifier: Programming Language :: Python :: 3.11
Requires-Dist: Pillow (>=9.4.0,<10.0.0)
Requires-Dist: circlify (>=0.15.0,<0.16.0)
Requires-Dist: imageio (>=2.27.0,<3.0.0)
Requires-Dist: numpy (>=1.24.2,<2.0.0)
Requires-Dist: pathvalidate (>=2.5.2,<3.0.0)
Requires-Dist: pip (>=22.3.1,<23.0.0)
Requires-Dist: python-dateutil (>=2.8.2,<3.0.0)
Requires-Dist: python-dotenv (>=1.0.0,<2.0.0)
Requires-Dist: requests (>=2.28.2,<3.0.0)
Requires-Dist: requests-futures (>=1.0.0,<2.0.0)
Requires-Dist: setuptools (>=65.5.1,<66.0.0)
Requires-Dist: six (>=1.16.0,<2.0.0)
Requires-Dist: urllib3 (>=1.26.15,<2.0.0)
Requires-Dist: wheel (>=0.38.4,<0.39.0)
